hitz/__init__.py
hitz-0.1.0.dist-info/METADATA
hitz-0.1.0.dist-info/WHEEL
hitz-0.1.0.dist-info/RECORD
