Metadata-Version: 2.1
Name: hitz
Version: 0.1.0
Summary: 
Author: P3tru
Author-email: stephane.zsoldos@gmail.com
Requires-Python: >=3.5,<4.0
Classifier: Programming Language :: Python :: 3
Classifier: Programming Language :: Python :: 3.5
Classifier: Programming Language :: Python :: 3.6
Classifier: Programming Language :: Python :: 3.7
Classifier: Programming Language :: Python :: 3.8
Classifier: Programming Language :: Python :: 3.9
Classifier: Programming Language :: Python :: 3.10
Classifier: Programming Language :: Python :: 3.11
Requires-Dist: coordz (>=0.1.1,<0.2.0)
